odoo/addons/stock_helper/README.rst
odoo/addons/stock_helper/__init__.py
odoo/addons/stock_helper/__manifest__.py
odoo/addons/stock_helper/i18n/it.po
odoo/addons/stock_helper/i18n/stock_helper.pot
odoo/addons/stock_helper/models/__init__.py
odoo/addons/stock_helper/models/stock_location.py
odoo/addons/stock_helper/readme/CONTRIBUTORS.rst
odoo/addons/stock_helper/readme/DESCRIPTION.rst
odoo/addons/stock_helper/static/description/icon.png
odoo/addons/stock_helper/static/description/index.html
odoo/addons/stock_helper/tests/__init__.py
odoo/addons/stock_helper/tests/common.py
odoo/addons/stock_helper/tests/test_location_get_closest_warehouse.py
odoo/addons/stock_helper/tests/test_location_is_sublocation_of.py
odoo/addons/stock_helper/tests/test_location_source_from_route.py
odoo14_addon_stock_helper-14.0.1.3.0.dist-info/METADATA
odoo14_addon_stock_helper-14.0.1.3.0.dist-info/WHEEL
odoo14_addon_stock_helper-14.0.1.3.0.dist-info/top_level.txt
odoo14_addon_stock_helper-14.0.1.3.0.dist-info/RECORD
